django_model_query_graphs/__init__.py
Django_Model_Query_Graphs-0.0.5.dist-info/LICENSE
Django_Model_Query_Graphs-0.0.5.dist-info/METADATA
Django_Model_Query_Graphs-0.0.5.dist-info/WHEEL
Django_Model_Query_Graphs-0.0.5.dist-info/top_level.txt
Django_Model_Query_Graphs-0.0.5.dist-info/RECORD
