Metadata-Version: 2.1
Name: Django-Model-Query-Graphs
Version: 0.0.5
Summary: Django Model Query Graphs
Home-page: https://GitHub.com/TheVinhLuong102/Django-Model-Query-Graphs
Author: TheVinhLuong102
Author-email: TheVinhLuong@GMail.com
License: UNKNOWN
Keywords: Django Model Query Graphs
Platform: UNKNOWN
Requires-Dist: Django-Polymorphic (>=3.0.0)
Requires-Dist: Django (>=3.1.4)
